setup.py
aulaPyPratico/__init__.py
aulaPyPratico/catalogo.py
aulaPyPratico/github.py
aulaPyPratico.egg-info/PKG-INFO
aulaPyPratico.egg-info/SOURCES.txt
aulaPyPratico.egg-info/dependency_links.txt
aulaPyPratico.egg-info/not-zip-safe
aulaPyPratico.egg-info/requires.txt
aulaPyPratico.egg-info/top_level.txt