Metadata-Version: 1.1
Name: aulaPyPratico
Version: 0.1
Summary: Teste PyPratico - xmltodict
Home-page: https://github.com/amaurirg/reqgithub
Author: Amauri Rossetti Giovani
Author-email: amauri.giovani@gmail.com
License: BSD
Platform: UNKNOWN
Classifier: Development Status :: 4 - Beta
Classifier: Environment :: Web Environment
Classifier: Intended Audience :: Developers
Classifier: License :: OSI Approved :: BSD License
Classifier: Operating System :: OS Independent
Classifier: Programming Language :: Python
Classifier: Framework :: Paste
